bas_remote/__init__.py
bas_remote/client.py
bas_remote/errors.py
bas_remote/options.py
bas_remote/runners/__init__.py
bas_remote/runners/function.py
bas_remote/runners/runner.py
bas_remote/runners/thread.py
bas_remote/services/__init__.py
bas_remote/services/engine_service.py
bas_remote/services/socket_service.py
bas_remote/types/__init__.py
bas_remote/types/message.py
bas_remote/types/response.py
bas_remote/types/script.py
bas_remote_python-1.7.dist-info/licenses/LICENSE.md
tests/__init__.py
tests/integration/__init__.py
tests/integration/base.py
tests/integration/functions_client_test.py
tests/integration/functions_thread_test.py
tests/integration/helpers.py
tests/types/__init__.py
tests/types/message_test.py
tests/types/response_test.py
bas_remote_python-1.7.dist-info/METADATA
bas_remote_python-1.7.dist-info/WHEEL
bas_remote_python-1.7.dist-info/top_level.txt
bas_remote_python-1.7.dist-info/RECORD
