Metadata-Version: 2.4
Name: bas-remote-python
Version: 1.7
Summary: Python library, which allows you to automate Google Chrome browser.
Home-page: https://github.com/bablosoft/bas-remote-python
Author: bablosoft
Author-email: mail.to.twaego@gmail.com
License: MIT
Project-URL: Documentation, https://github.com/bablosoft/bas-remote-python/wiki
Keywords: visual-programming-language,browserautomationstudio,bas-remote-control,bas-remote-client,bot-framework,bas-remote,bas-client,automation,chromium,imacros,windows,desktop,browser,grabber,poster,macros,bas,ide,cef,bot
Classifier: Intended Audience :: Developers
Classifier: Programming Language :: Python :: 3
Classifier: Programming Language :: Python :: 3.7
Classifier: Programming Language :: Python :: 3.8
Classifier: Programming Language :: Python :: 3.9
Classifier: Programming Language :: Python :: 3.10
Classifier: Programming Language :: Python :: 3.11
Classifier: Programming Language :: Python :: 3.12
Classifier: License :: OSI Approved :: MIT License
Requires-Python: >=3.7
License-File: LICENSE.md
Requires-Dist: dataclasses_json>=0.5.7
Requires-Dist: filelock>=3.8.2
Requires-Dist: packaging>=24.1
Requires-Dist: websockets>=10.4
Requires-Dist: aiofiles>=0.8.0
Requires-Dist: aiohttp>=3.10.5
Requires-Dist: pyee>=9.0.4
Dynamic: author
Dynamic: author-email
Dynamic: classifier
Dynamic: description
Dynamic: description-content-type
Dynamic: home-page
Dynamic: keywords
Dynamic: license
Dynamic: license-file
Dynamic: project-url
Dynamic: requires-dist
Dynamic: requires-python
Dynamic: summary
